benzema/__init__.py
benzema/constants.py
benzema/decoder.py
benzema/encoder.py
benzema-0.1.2.dist-info/LICENSE
benzema-0.1.2.dist-info/WHEEL
benzema-0.1.2.dist-info/METADATA
benzema-0.1.2.dist-info/RECORD
